nebulous/__init__.py
nebulous-0.0.1.dist-info/LICENSE.txt
nebulous-0.0.1.dist-info/METADATA
nebulous-0.0.1.dist-info/WHEEL
nebulous-0.0.1.dist-info/top_level.txt
nebulous-0.0.1.dist-info/RECORD
