Metadata-Version: 2.1
Name: nebulous
Version: 0.0.1
Summary: Nebulous SDK
Home-page: UNKNOWN
Author: Peter-Jan Brone
Author-email: peterjan.brone@gmail.com
License: UNKNOWN
Platform: UNKNOWN
Classifier: Programming Language :: Python :: 3
Classifier: License :: OSI Approved :: MIT License
Classifier: Operating System :: OS Independent
Requires-Python: >=3.6
